sms.py
twilioSMS.py
twilioSMS-1.1.3.dist-info/LICENSE
twilioSMS-1.1.3.dist-info/METADATA
twilioSMS-1.1.3.dist-info/WHEEL
twilioSMS-1.1.3.dist-info/top_level.txt
twilioSMS-1.1.3.dist-info/RECORD
