Metadata-Version: 2.1
Name: twilioSMS
Version: 1.1.3
Summary: a fun texting app
Home-page: UNKNOWN
License: UNKNOWN
Keywords: twilioSMS,twilio
Platform: UNKNOWN
Classifier: Programming Language :: Python :: 3
Classifier: License :: OSI Approved :: MIT License
Classifier: Operating System :: OS Independent
Requires-Python: >=3
Requires-Dist: twilio (>=6.38.1)
